chrome_pool/__init__.py
chrome_pool/chrome_pool.py
selenium_chrome_pool-0.1.5.dist-info/METADATA
selenium_chrome_pool-0.1.5.dist-info/WHEEL
selenium_chrome_pool-0.1.5.dist-info/top_level.txt
selenium_chrome_pool-0.1.5.dist-info/RECORD
