Metadata-Version: 2.1
Name: selenium-chrome-pool
Version: 0.1.5
Summary: A Python library for managing Selenium Chrome connections.
Home-page: https://github.com/meihuabo/selenium_chrome_pool
Author: meihuabo
Author-email: meihuabo@163.com
Classifier: Programming Language :: Python :: 3
Classifier: License :: OSI Approved :: MIT License
Classifier: Operating System :: OS Independent
Requires-Python: >=3.6
Requires-Dist: selenium
